runradarrun/ingest.py
runradarrun/main.py
runradarrun/model.py
runradarrun/output.py
runradarrun/publishers/twbyor.py
runradarrun/publishers/zalando.py
run_radar_run-0.1.dist-info/METADATA
run_radar_run-0.1.dist-info/WHEEL
run_radar_run-0.1.dist-info/entry_points.txt
run_radar_run-0.1.dist-info/RECORD
