Metadata-Version: 2.3
Name: run-radar-run
Version: 0.1
Summary: Run, Radar, Run - Running your own tech radar should be easy
License: MIT
Keywords: tech-radar
Author: Alexei Znamensky
Author-email: russoz@gmail.com
Requires-Python: >=3.12,<4.0
Classifier: Development Status :: 2 - Pre-Alpha
Classifier: Environment :: Console
Classifier: Intended Audience :: Information Technology
Classifier: License :: OSI Approved :: MIT License
Classifier: Operating System :: OS Independent
Classifier: Programming Language :: Python
Classifier: Programming Language :: Python :: 3
Classifier: Programming Language :: Python :: 3.12
Classifier: Programming Language :: Python :: 3.13
Classifier: Topic :: Software Development :: Testing
Classifier: Topic :: Utilities
Requires-Dist: blessed (>=1.20.0)
Requires-Dist: docker (>=7.1.0)
Requires-Dist: gitpython (>=3.1.44)
Requires-Dist: pyyaml (>=5.4)
